setup.py
paradox_commons/__init__.py
paradox_commons/common_date.py
paradox_commons.egg-info/PKG-INFO
paradox_commons.egg-info/SOURCES.txt
paradox_commons.egg-info/dependency_links.txt
paradox_commons.egg-info/top_level.txt