Metadata-Version: 1.0
Name: paradox-commons
Version: 0.0.1
Summary: Paradox's common methods
Home-page: https://github.com/13241308289/paradox_common
Author: ZhangLe
Author-email: 2519960931@qq.com
License: MIT Licence
Keywords: pip,paradox_commons,paradox_commons
Platform: any
